pywingui/__init__.py
pywingui/ai_agent_error_engine.cp312-win_amd64.pyd
pywingui/controller.cp312-win_amd64.pyd
pywingui/runtime_guard.cp312-win_amd64.pyd
pywingui/win32_child_error_handler.cp312-win_amd64.pyd
pywingui-4.2.9.dist-info/METADATA
pywingui-4.2.9.dist-info/WHEEL
pywingui-4.2.9.dist-info/top_level.txt
pywingui-4.2.9.dist-info/RECORD
