Metadata-Version: 2.4
Name: pywingui
Version: 4.2.9
Summary: PyWinGUI GUI Automation Library for Windows Forms (Binary Distribution)
Author: User
Requires-Python: <3.14,>=3.11
Requires-Dist: pywinauto
Requires-Dist: requests
Requires-Dist: pyautogui
Requires-Dist: pywin32
Requires-Dist: pillow
Requires-Dist: cryptography
Requires-Dist: pygetwindow
Requires-Dist: opencv-python
